autora/experimentalist/bandit_random/__init__.py
bandit_random-0.0.1.dist-info/LICENSE
bandit_random-0.0.1.dist-info/METADATA
bandit_random-0.0.1.dist-info/WHEEL
bandit_random-0.0.1.dist-info/top_level.txt
bandit_random-0.0.1.dist-info/RECORD
