Metadata-Version: 2.1
Name: bandit-random
Version: 0.0.1
Summary: Create a sequence of bandit task rewards using iniitial reward probabilty and drift
Author-email: Younes Strittmatter <ystrittm@gmail.com>
License: Copyright (c) 2024 Younes Strittmatter
Project-URL: homepage, http://www.empiricalresearch.ai
Project-URL: repository, https://github.com/AutoResearch/autora-experimentalist-bandit-random
Project-URL: documentation, https://autoresearch.github.io/autora/
Requires-Python: <4,>=3.8
License-File: LICENSE
Requires-Dist: autora-core
Requires-Dist: scikit-learn
Provides-Extra: dev
Requires-Dist: autora-core[dev] ; extra == 'dev'
